zunzun/__init__.py
zunzun/core_app.py
zunzun/import_string.py
zunzun/inspect.py
zunzun/app/__init__.py
zunzun/app/app.py
zunzun/app/app_register.py
zunzun/apps/__init__.py
zunzun/apps/maker/__init__.py
zunzun/apps/maker/app.py
zunzun/apps/maker/commands/__init__.py
zunzun/apps/maker/commands/base_command.py
zunzun/apps/maker/commands/class_creator.py
zunzun/apps/maker/commands/command.py
zunzun/apps/maker/commands/controller.py
zunzun/apps/maker/commands/listener.py
zunzun/apps/maker/commands/service.py
zunzun/apps/maker/commands/signal.py
zunzun/apps/orm/__init__.py
zunzun/apps/orm/app.py
zunzun/apps/orm/base.py
zunzun/apps/orm/base_repository.py
zunzun/apps/orm/engine.py
zunzun/apps/orm/session.py
zunzun/apps/orm/commands/__init__.py
zunzun/apps/orm/commands/model_create.py
zunzun/apps/orm/commands/shema_create.py
zunzun/command/__init__.py
zunzun/command/command.py
zunzun/command/command_register.py
zunzun/command/exceptions.py
zunzun/commands/__init__.py
zunzun/commands/run_server.py
zunzun/config/__init__.py
zunzun/config/config.py
zunzun/config/config_decorator.py
zunzun/http_kernel/__init__.py
zunzun/http_kernel/kernel.py
zunzun/http_kernel/request.py
zunzun/http_kernel/response.py
zunzun/http_kernel/router.py
zunzun/signals/__init__.py
zunzun/signals/listerner_connector.py
zunzun/signals/signal.py
zunzun/testing/__init__.py
zunzun/testing/client.py
zunzun-0.0.2.dist-info/LICENSE
zunzun-0.0.2.dist-info/METADATA
zunzun-0.0.2.dist-info/WHEEL
zunzun-0.0.2.dist-info/top_level.txt
zunzun-0.0.2.dist-info/RECORD
