Metadata-Version: 2.1
Name: zunzun
Version: 0.0.2
Summary: A python framework to create api applications.
Home-page: https://github.com/aprezcuba24/zunzun
Author: Renier Ricardo Figueredo
Author-email: aprezcuba24@gmail.com
License: UNKNOWN
Platform: UNKNOWN
Classifier: Programming Language :: Python :: 3
Classifier: License :: OSI Approved :: MIT License
Classifier: Operating System :: OS Independent
Requires-Python: >=3.6
